{
  "lookup": {
    "rules": {
      "[{\"prev_action\": {\"action_name\": \"action_listen\"}, \"user\": {\"intent\": \"vuon_hoa_thanh_pho\"}}]": "utter_vuon_hoa",
      "[{\"prev_action\": {\"action_name\": \"action_listen\"}, \"user\": {\"intent\": \"vuon_hoa_thanh_pho\"}}, {\"prev_action\": {\"action_name\": \"utter_vuon_hoa\"}, \"user\": {\"intent\": \"vuon_hoa_thanh_pho\"}}]": "action_listen",
      "[{\"prev_action\": {\"action_name\": \"action_listen\"}, \"user\": {\"intent\": \"nha_hang_ngon_vila\"}}]": "utter_nhahangngonVilla",
      "[{\"prev_action\": {\"action_name\": \"action_listen\"}, \"user\": {\"intent\": \"nha_hang_ngon_vila\"}}, {\"prev_action\": {\"action_name\": \"utter_nhahangngonVilla\"}, \"user\": {\"intent\": \"nha_hang_ngon_vila\"}}]": "action_listen",
      "[{\"prev_action\": {\"action_name\": \"action_listen\"}, \"user\": {\"intent\": \"nha_tho_domaine_de_marie\"}}]": "utter_domaine",
      "[{\"prev_action\": {\"action_name\": \"action_listen\"}, \"user\": {\"intent\": \"nha_tho_domaine_de_marie\"}}, {\"prev_action\": {\"action_name\": \"utter_domaine\"}, \"user\": {\"intent\": \"nha_tho_domaine_de_marie\"}}]": "action_listen",
      "[{\"prev_action\": {\"action_name\": \"action_listen\"}, \"user\": {\"intent\": \"goodbye\"}}]": "utter_goodbye",
      "[{\"prev_action\": {\"action_name\": \"action_listen\"}, \"user\": {\"intent\": \"goodbye\"}}, {\"prev_action\": {\"action_name\": \"utter_goodbye\"}, \"user\": {\"intent\": \"goodbye\"}}]": "action_listen",
      "[{\"prev_action\": {\"action_name\": \"action_listen\"}, \"user\": {\"intent\": \"more_info_xuan_huong_lake\"}}]": "action_more_info_xuan_huong_lake",
      "[{\"prev_action\": {\"action_name\": \"action_listen\"}, \"user\": {\"intent\": \"more_info_xuan_huong_lake\"}}, {\"prev_action\": {\"action_name\": \"action_more_info_xuan_huong_lake\"}, \"user\": {\"intent\": \"more_info_xuan_huong_lake\"}}]": "action_listen",
      "[{\"prev_action\": {\"action_name\": \"action_listen\"}, \"user\": {\"intent\": \"thung_lung_tinh_yeu\"}}]": "utter_thung_lung",
      "[{\"prev_action\": {\"action_name\": \"action_listen\"}, \"user\": {\"intent\": \"thung_lung_tinh_yeu\"}}, {\"prev_action\": {\"action_name\": \"utter_thung_lung\"}, \"user\": {\"intent\": \"thung_lung_tinh_yeu\"}}]": "action_listen",
      "[{\"prev_action\": {\"action_name\": \"action_listen\"}, \"user\": {\"intent\": \"dia_diem_an_uong\"}}]": "utter_food_time",
      "[{\"prev_action\": {\"action_name\": \"action_listen\"}, \"user\": {\"intent\": \"dia_diem_an_uong\"}}, {\"prev_action\": {\"action_name\": \"utter_food_time\"}, \"user\": {\"intent\": \"dia_diem_an_uong\"}}]": "action_listen",
      "[{\"prev_action\": {\"action_name\": \"action_listen\"}, \"user\": {\"intent\": \"greet\"}}]": "utter_greet",
      "[{\"prev_action\": {\"action_name\": \"action_listen\"}, \"user\": {\"intent\": \"greet\"}}, {\"prev_action\": {\"action_name\": \"utter_greet\"}, \"user\": {\"intent\": \"greet\"}}]": "action_listen",
      "[{\"prev_action\": {\"action_name\": \"action_listen\"}, \"user\": {\"intent\": \"go_dalat\"}}]": "utter_Go_DaLat",
      "[{\"prev_action\": {\"action_name\": \"action_listen\"}, \"user\": {\"intent\": \"go_dalat\"}}, {\"prev_action\": {\"action_name\": \"utter_Go_DaLat\"}, \"user\": {\"intent\": \"go_dalat\"}}]": "action_listen",
      "[{\"prev_action\": {\"action_name\": \"action_listen\"}, \"user\": {\"intent\": \"bot_challenge\"}}]": "utter_iamabot",
      "[{\"prev_action\": {\"action_name\": \"action_listen\"}, \"user\": {\"intent\": \"bot_challenge\"}}, {\"prev_action\": {\"action_name\": \"utter_iamabot\"}, \"user\": {\"intent\": \"bot_challenge\"}}]": "action_listen",
      "[{\"prev_action\": {\"action_name\": \"action_listen\"}, \"user\": {\"intent\": \"coopmart_dalat\"}}]": "utter_Co_opmart",
      "[{\"prev_action\": {\"action_name\": \"action_listen\"}, \"user\": {\"intent\": \"coopmart_dalat\"}}, {\"prev_action\": {\"action_name\": \"utter_Co_opmart\"}, \"user\": {\"intent\": \"coopmart_dalat\"}}]": "action_listen",
      "[{\"prev_action\": {\"action_name\": \"action_listen\"}, \"user\": {\"intent\": \"banh_trang_nuong\"}}]": "utter_banhtrangnuong",
      "[{\"prev_action\": {\"action_name\": \"action_listen\"}, \"user\": {\"intent\": \"banh_trang_nuong\"}}, {\"prev_action\": {\"action_name\": \"utter_banhtrangnuong\"}, \"user\": {\"intent\": \"banh_trang_nuong\"}}]": "action_listen",
      "[{\"prev_action\": {\"action_name\": \"action_listen\"}, \"user\": {\"intent\": \"quan_che_thanh_thao\"}}]": "utter_quancheThanhThao",
      "[{\"prev_action\": {\"action_name\": \"action_listen\"}, \"user\": {\"intent\": \"quan_che_thanh_thao\"}}, {\"prev_action\": {\"action_name\": \"utter_quancheThanhThao\"}, \"user\": {\"intent\": \"quan_che_thanh_thao\"}}]": "action_listen",
      "[{\"prev_action\": {\"action_name\": \"action_listen\"}, \"user\": {\"intent\": \"quan_an_ly_hoa_sua\"}}]": "utter_quananLyHoaSua",
      "[{\"prev_action\": {\"action_name\": \"action_listen\"}, \"user\": {\"intent\": \"quan_an_ly_hoa_sua\"}}, {\"prev_action\": {\"action_name\": \"utter_quananLyHoaSua\"}, \"user\": {\"intent\": \"quan_an_ly_hoa_sua\"}}]": "action_listen",
      "[{\"prev_action\": {\"action_name\": \"action_listen\"}, \"user\": {\"intent\": \"nha_tho_con_ga\"}}]": "utter_conga",
      "[{\"prev_action\": {\"action_name\": \"action_listen\"}, \"user\": {\"intent\": \"nha_tho_con_ga\"}}, {\"prev_action\": {\"action_name\": \"utter_conga\"}, \"user\": {\"intent\": \"nha_tho_con_ga\"}}]": "action_listen",
      "[{\"prev_action\": {\"action_name\": \"action_listen\"}, \"user\": {\"intent\": \"doi_robin\"}}]": "utter_robon",
      "[{\"prev_action\": {\"action_name\": \"action_listen\"}, \"user\": {\"intent\": \"doi_robin\"}}, {\"prev_action\": {\"action_name\": \"utter_robon\"}, \"user\": {\"intent\": \"doi_robin\"}}]": "action_listen",
      "[{\"prev_action\": {\"action_name\": \"action_listen\"}, \"user\": {\"intent\": \"thac_Pongour\"}}]": "utter_thacPongour",
      "[{\"prev_action\": {\"action_name\": \"action_listen\"}, \"user\": {\"intent\": \"thac_Pongour\"}}, {\"prev_action\": {\"action_name\": \"utter_thacPongour\"}, \"user\": {\"intent\": \"thac_Pongour\"}}]": "action_listen",
      "[{\"prev_action\": {\"action_name\": \"action_listen\"}, \"user\": {\"intent\": \"dinh_bao_dai\"}}]": "utter_dinhbaodai",
      "[{\"prev_action\": {\"action_name\": \"action_listen\"}, \"user\": {\"intent\": \"dinh_bao_dai\"}}, {\"prev_action\": {\"action_name\": \"utter_dinhbaodai\"}, \"user\": {\"intent\": \"dinh_bao_dai\"}}]": "action_listen",
      "[{\"prev_action\": {\"action_name\": \"action_listen\"}, \"user\": {\"intent\": \"chua_linh_phuoc\"}}]": "utter_chualinhphuoc",
      "[{\"prev_action\": {\"action_name\": \"action_listen\"}, \"user\": {\"intent\": \"chua_linh_phuoc\"}}, {\"prev_action\": {\"action_name\": \"utter_chualinhphuoc\"}, \"user\": {\"intent\": \"chua_linh_phuoc\"}}]": "action_listen",
      "[{\"prev_action\": {\"action_name\": \"action_listen\"}, \"user\": {\"intent\": \"cung_dien_tran_le_xuan\"}}]": "utter_tranlexuan",
      "[{\"prev_action\": {\"action_name\": \"action_listen\"}, \"user\": {\"intent\": \"cung_dien_tran_le_xuan\"}}, {\"prev_action\": {\"action_name\": \"utter_tranlexuan\"}, \"user\": {\"intent\": \"cung_dien_tran_le_xuan\"}}]": "action_listen",
      "[{\"prev_action\": {\"action_name\": \"action_listen\"}, \"user\": {\"intent\": \"hem_32\"}}]": "utter_hem32",
      "[{\"prev_action\": {\"action_name\": \"action_listen\"}, \"user\": {\"intent\": \"hem_32\"}}, {\"prev_action\": {\"action_name\": \"utter_hem32\"}, \"user\": {\"intent\": \"hem_32\"}}]": "action_listen",
      "[{\"prev_action\": {\"action_name\": \"action_listen\"}, \"user\": {\"intent\": \"quan_cafe_vuon\"}}]": "utter_cafeVuon",
      "[{\"prev_action\": {\"action_name\": \"action_listen\"}, \"user\": {\"intent\": \"quan_cafe_vuon\"}}, {\"prev_action\": {\"action_name\": \"utter_cafeVuon\"}, \"user\": {\"intent\": \"quan_cafe_vuon\"}}]": "action_listen",
      "[{\"prev_action\": {\"action_name\": \"action_listen\"}, \"user\": {\"intent\": \"quan_com_ga_ba_hanh\"}}]": "utter_quancomgaBaHanh",
      "[{\"prev_action\": {\"action_name\": \"action_listen\"}, \"user\": {\"intent\": \"quan_com_ga_ba_hanh\"}}, {\"prev_action\": {\"action_name\": \"utter_quancomgaBaHanh\"}, \"user\": {\"intent\": \"quan_com_ga_ba_hanh\"}}]": "action_listen",
      "[{\"prev_action\": {\"action_name\": \"action_listen\"}, \"user\": {\"intent\": \"cho_dalat\"}}]": "utter_chodalat",
      "[{\"prev_action\": {\"action_name\": \"action_listen\"}, \"user\": {\"intent\": \"cho_dalat\"}}, {\"prev_action\": {\"action_name\": \"utter_chodalat\"}, \"user\": {\"intent\": \"cho_dalat\"}}]": "action_listen"
    },
    "rule_only_slots": [],
    "rule_only_loops": [],
    "rules_for_loop_unhappy_path": {},
    "rules_not_in_stories": [
      "[{\"prev_action\": {\"action_name\": \"action_listen\"}, \"user\": {\"intent\": \"cung_dien_tran_le_xuan\"}}]",
      "[{\"prev_action\": {\"action_name\": \"action_listen\"}, \"user\": {\"intent\": \"cung_dien_tran_le_xuan\"}}, {\"prev_action\": {\"action_name\": \"utter_tranlexuan\"}, \"user\": {\"intent\": \"cung_dien_tran_le_xuan\"}}]",
      "[{\"prev_action\": {\"action_name\": \"action_listen\"}, \"user\": {\"intent\": \"dinh_bao_dai\"}}]",
      "[{\"prev_action\": {\"action_name\": \"action_listen\"}, \"user\": {\"intent\": \"nha_tho_domaine_de_marie\"}}, {\"prev_action\": {\"action_name\": \"utter_domaine\"}, \"user\": {\"intent\": \"nha_tho_domaine_de_marie\"}}]",
      "[{\"prev_action\": {\"action_name\": \"action_listen\"}, \"user\": {\"intent\": \"quan_cafe_vuon\"}}]",
      "[{\"prev_action\": {\"action_name\": \"action_listen\"}, \"user\": {\"intent\": \"doi_robin\"}}, {\"prev_action\": {\"action_name\": \"utter_robon\"}, \"user\": {\"intent\": \"doi_robin\"}}]",
      "[{\"prev_action\": {\"action_name\": \"action_listen\"}, \"user\": {\"intent\": \"vuon_hoa_thanh_pho\"}}, {\"prev_action\": {\"action_name\": \"utter_vuon_hoa\"}, \"user\": {\"intent\": \"vuon_hoa_thanh_pho\"}}]",
      "[{\"prev_action\": {\"action_name\": \"action_listen\"}, \"user\": {\"intent\": \"coopmart_dalat\"}}]",
      "[{\"prev_action\": {\"action_name\": \"action_listen\"}, \"user\": {\"intent\": \"doi_robin\"}}]",
      "[{\"prev_action\": {\"action_name\": \"action_listen\"}, \"user\": {\"intent\": \"nha_hang_ngon_vila\"}}]",
      "[{\"prev_action\": {\"action_name\": \"action_listen\"}, \"user\": {\"intent\": \"chua_linh_phuoc\"}}]",
      "[{\"prev_action\": {\"action_name\": \"action_listen\"}, \"user\": {\"intent\": \"bot_challenge\"}}]",
      "[{\"prev_action\": {\"action_name\": \"action_listen\"}, \"user\": {\"intent\": \"goodbye\"}}, {\"prev_action\": {\"action_name\": \"utter_goodbye\"}, \"user\": {\"intent\": \"goodbye\"}}]",
      "predicting default action with intent back",
      "[{\"prev_action\": {\"action_name\": \"action_listen\"}, \"user\": {\"intent\": \"thac_Pongour\"}}, {\"prev_action\": {\"action_name\": \"utter_thacPongour\"}, \"user\": {\"intent\": \"thac_Pongour\"}}]",
      "[{\"prev_action\": {\"action_name\": \"action_listen\"}, \"user\": {\"intent\": \"nha_tho_con_ga\"}}]",
      "[{\"prev_action\": {\"action_name\": \"action_listen\"}, \"user\": {\"intent\": \"quan_cafe_vuon\"}}, {\"prev_action\": {\"action_name\": \"utter_cafeVuon\"}, \"user\": {\"intent\": \"quan_cafe_vuon\"}}]",
      "[{\"prev_action\": {\"action_name\": \"action_listen\"}, \"user\": {\"intent\": \"cho_dalat\"}}, {\"prev_action\": {\"action_name\": \"utter_chodalat\"}, \"user\": {\"intent\": \"cho_dalat\"}}]",
      "[{\"prev_action\": {\"action_name\": \"action_listen\"}, \"user\": {\"intent\": \"go_dalat\"}}, {\"prev_action\": {\"action_name\": \"utter_Go_DaLat\"}, \"user\": {\"intent\": \"go_dalat\"}}]",
      "[{\"prev_action\": {\"action_name\": \"action_listen\"}, \"user\": {\"intent\": \"nha_hang_ngon_vila\"}}, {\"prev_action\": {\"action_name\": \"utter_nhahangngonVilla\"}, \"user\": {\"intent\": \"nha_hang_ngon_vila\"}}]",
      "[{\"prev_action\": {\"action_name\": \"action_listen\"}, \"user\": {\"intent\": \"nha_tho_con_ga\"}}, {\"prev_action\": {\"action_name\": \"utter_conga\"}, \"user\": {\"intent\": \"nha_tho_con_ga\"}}]",
      "[{\"prev_action\": {\"action_name\": \"action_listen\"}, \"user\": {\"intent\": \"banh_trang_nuong\"}}]",
      "[{\"prev_action\": {\"action_name\": \"action_listen\"}, \"user\": {\"intent\": \"go_dalat\"}}]",
      "[{\"prev_action\": {\"action_name\": \"action_listen\"}, \"user\": {\"intent\": \"dinh_bao_dai\"}}, {\"prev_action\": {\"action_name\": \"utter_dinhbaodai\"}, \"user\": {\"intent\": \"dinh_bao_dai\"}}]",
      "predicting default action with intent restart",
      "[{\"prev_action\": {\"action_name\": \"action_listen\"}, \"user\": {\"intent\": \"hem_32\"}}]",
      "[{\"prev_action\": {\"action_name\": \"action_listen\"}, \"user\": {\"intent\": \"nha_tho_domaine_de_marie\"}}]",
      "[{\"prev_action\": {\"action_name\": \"action_listen\"}, \"user\": {\"intent\": \"quan_com_ga_ba_hanh\"}}, {\"prev_action\": {\"action_name\": \"utter_quancomgaBaHanh\"}, \"user\": {\"intent\": \"quan_com_ga_ba_hanh\"}}]",
      "[{\"prev_action\": {\"action_name\": \"action_listen\"}, \"user\": {\"intent\": \"quan_che_thanh_thao\"}}, {\"prev_action\": {\"action_name\": \"utter_quancheThanhThao\"}, \"user\": {\"intent\": \"quan_che_thanh_thao\"}}]",
      "[{\"prev_action\": {\"action_name\": \"action_listen\"}, \"user\": {\"intent\": \"quan_an_ly_hoa_sua\"}}, {\"prev_action\": {\"action_name\": \"utter_quananLyHoaSua\"}, \"user\": {\"intent\": \"quan_an_ly_hoa_sua\"}}]",
      "[{\"prev_action\": {\"action_name\": \"action_listen\"}, \"user\": {\"intent\": \"coopmart_dalat\"}}, {\"prev_action\": {\"action_name\": \"utter_Co_opmart\"}, \"user\": {\"intent\": \"coopmart_dalat\"}}]",
      "[{\"prev_action\": {\"action_name\": \"action_listen\"}, \"user\": {\"intent\": \"thac_Pongour\"}}]",
      "[{\"prev_action\": {\"action_name\": \"action_listen\"}, \"user\": {\"intent\": \"thung_lung_tinh_yeu\"}}, {\"prev_action\": {\"action_name\": \"utter_thung_lung\"}, \"user\": {\"intent\": \"thung_lung_tinh_yeu\"}}]",
      "[{\"prev_action\": {\"action_name\": \"action_listen\"}, \"user\": {\"intent\": \"chua_linh_phuoc\"}}, {\"prev_action\": {\"action_name\": \"utter_chualinhphuoc\"}, \"user\": {\"intent\": \"chua_linh_phuoc\"}}]",
      "[{\"prev_action\": {\"action_name\": \"action_listen\"}, \"user\": {\"intent\": \"cho_dalat\"}}]",
      "[{\"prev_action\": {\"action_name\": \"action_listen\"}, \"user\": {\"intent\": \"thung_lung_tinh_yeu\"}}]",
      "[{\"prev_action\": {\"action_name\": \"action_listen\"}, \"user\": {\"intent\": \"goodbye\"}}]",
      "[{\"prev_action\": {\"action_name\": \"action_listen\"}, \"user\": {\"intent\": \"hem_32\"}}, {\"prev_action\": {\"action_name\": \"utter_hem32\"}, \"user\": {\"intent\": \"hem_32\"}}]",
      "[{\"prev_action\": {\"action_name\": \"action_listen\"}, \"user\": {\"intent\": \"quan_com_ga_ba_hanh\"}}]",
      "[{\"prev_action\": {\"action_name\": \"action_listen\"}, \"user\": {\"intent\": \"banh_trang_nuong\"}}, {\"prev_action\": {\"action_name\": \"utter_banhtrangnuong\"}, \"user\": {\"intent\": \"banh_trang_nuong\"}}]",
      "[{\"prev_action\": {\"action_name\": \"action_listen\"}, \"user\": {\"intent\": \"quan_an_ly_hoa_sua\"}}]",
      "[{\"prev_action\": {\"action_name\": \"action_listen\"}, \"user\": {\"intent\": \"bot_challenge\"}}, {\"prev_action\": {\"action_name\": \"utter_iamabot\"}, \"user\": {\"intent\": \"bot_challenge\"}}]",
      "predicting default action with intent session_start",
      "[{\"prev_action\": {\"action_name\": \"action_listen\"}, \"user\": {\"intent\": \"vuon_hoa_thanh_pho\"}}]",
      "[{\"prev_action\": {\"action_name\": \"action_listen\"}, \"user\": {\"intent\": \"quan_che_thanh_thao\"}}]"
    ]
  }
}